README.md
setup.py
digitalocean/Account.py
digitalocean/Action.py
digitalocean/Certificate.py
digitalocean/Domain.py
digitalocean/Droplet.py
digitalocean/Firewall.py
digitalocean/FloatingIP.py
digitalocean/Image.py
digitalocean/Kernel.py
digitalocean/LoadBalancer.py
digitalocean/Manager.py
digitalocean/Metadata.py
digitalocean/Record.py
digitalocean/Region.py
digitalocean/SSHKey.py
digitalocean/Size.py
digitalocean/Snapshot.py
digitalocean/Tag.py
digitalocean/Volume.py
digitalocean/__init__.py
digitalocean/baseapi.py
python_digitalocean_latest.egg-info/PKG-INFO
python_digitalocean_latest.egg-info/SOURCES.txt
python_digitalocean_latest.egg-info/dependency_links.txt
python_digitalocean_latest.egg-info/requires.txt
python_digitalocean_latest.egg-info/top_level.txt