Metadata-Version: 1.0
Name: python-digitalocean-latest
Version: 1.14.1
Summary: digitalocean.com API to manage Droplets and Images
Home-page: https://github.com/koalalorenzo/python-digitalocean
Author: Lorenzo Setale ( http://who.is.lorenzo.setale.me/? )
Author-email: lorenzo@setale.me
License: LGPL v3
Platform: UNKNOWN
